Workbook
Name CategoryList: Categories!$A$2:$A$11
Name PaymentList: Categories!$D$2:$D$5

Sheet Instructions
A1: Simple Expense Tracker — How to Use
A3: 1. | B3: Open the Expenses sheet and add one row per expense.
A4: 2. | B4: Pick a Category and Payment Method from the dropdowns. The dropdowns are driven by the Categories sheet — edit that sheet to add or rename categories.
A5: 3. | B5: Enter the Amount as a positive number. Negative numbers are blocked.
A6: 4. | B6: Open the Summary sheet to see totals, by-category spend, budget vs actual, and the share-of-spending pie chart.
A7: 5. | B7: Set your monthly budget per category in column B of the Categories sheet. The Summary sheet will flag categories that are over budget.
A8: 6. | B8: To reuse the workbook for a new month, copy the file, then clear the rows under the headers on the Expenses sheet.
A10: Formulas used
A11: Total spent | B11: =SUM(ExpensesTbl[Amount])
A12: Spent per category | B12: =SUMIF(ExpensesTbl[Category], <category>, ExpensesTbl[Amount])
A13: Budget per category | B13: =VLOOKUP(<category>, Categories!A:B, 2, FALSE)
A14: Top category | B14: =INDEX(<cat range>, MATCH(MAX(<spent range>), <spent range>, 0))
A15: Over-budget count | B15: =COUNTIF(<remaining range>, "<0")

Sheet Expenses
A1: Date | B1: Category | C1: Description | D1: Payment Method | E1: Amount | F1: Notes
A2: 46143 | B2: Rent | C2: May rent | D2: Bank Transfer | E2: 1450
A3: 46144 | B3: Groceries | C3: Weekly shop | D3: Debit Card | E3: 82.45
A4: 46145 | B4: Dining Out | C4: Brunch with Sam | D4: Credit Card | E4: 34.1
A5: 46146 | B5: Transport | C5: Metro card top-up | D5: Debit Card | E5: 40
A6: 46147 | B6: Utilities | C6: Electricity bill | D6: Bank Transfer | E6: 78.2
A7: 46148 | B7: Subscriptions | C7: Streaming service | D7: Credit Card | E7: 14.99
A8: 46150 | B8: Groceries | C8: Mid-week top-up | D8: Debit Card | E8: 26.3
A9: 46151 | B9: Entertainment | C9: Cinema | D9: Credit Card | E9: 22
A10: 46152 | B10: Dining Out | C10: Pizza night | D10: Cash | E10: 18.5
A11: 46154 | B11: Health | C11: Pharmacy | D11: Debit Card | E11: 15.75
A12: 46155 | B12: Transport | C12: Rideshare home | D12: Credit Card | E12: 12.4
A13: 46157 | B13: Groceries | C13: Weekly shop | D13: Debit Card | E13: 94.1
... A23: 46172 | B23: Dining Out | C23: Family dinner | D23: Credit Card | E23: 62.45

Sheet Summary
A1: Monthly Expense Summary
A3: Reporting month | B3: 46143
A4: Last updated | B4: =TODAY()
A6: Total spent | C6: Number of expenses | E6: Average expense | G6: Largest expense
A7: =SUM(ExpensesTbl[Amount]) | C7: =COUNTA(ExpensesTbl[Amount]) | E7: =IFERROR(AVERAGE(ExpensesTbl[Amount]),0) | G7: =IFERROR(MAX(ExpensesTbl[Amount]),0)
A10: Spending by Category
A11: Category | B11: Spent | C11: Budget | D11: Remaining | E11: % of Total
A12: Rent | B12: =SUMIF(ExpensesTbl[Category],A12,ExpensesTbl[Amount]) | C12: =VLOOKUP(A12,Categories!$A$2:$B$11,2,FALSE) | D12: =C12-B12 | E12: =IFERROR(B12/$A$7,0)
A13: Groceries | B13: =SUMIF(ExpensesTbl[Category],A13,ExpensesTbl[Amount]) | C13: =VLOOKUP(A13,Categories!$A$2:$B$11,2,FALSE) | D13: =C13-B13 | E13: =IFERROR(B13/$A$7,0)
A14: Utilities | B14: =SUMIF(ExpensesTbl[Category],A14,ExpensesTbl[Amount]) | C14: =VLOOKUP(A14,Categories!$A$2:$B$11,2,FALSE) | D14: =C14-B14 | E14: =IFERROR(B14/$A$7,0)
A15: Transport | B15: =SUMIF(ExpensesTbl[Category],A15,ExpensesTbl[Amount]) | C15: =VLOOKUP(A15,Categories!$A$2:$B$11,2,FALSE) | D15: =C15-B15 | E15: =IFERROR(B15/$A$7,0)
A16: Dining Out | B16: =SUMIF(ExpensesTbl[Category],A16,ExpensesTbl[Amount]) | C16: =VLOOKUP(A16,Categories!$A$2:$B$11,2,FALSE) | D16: =C16-B16 | E16: =IFERROR(B16/$A$7,0)
A17: Entertainment | B17: =SUMIF(ExpensesTbl[Category],A17,ExpensesTbl[Amount]) | C17: =VLOOKUP(A17,Categories!$A$2:$B$11,2,FALSE) | D17: =C17-B17 | E17: =IFERROR(B17/$A$7,0)
A18: Health | B18: =SUMIF(ExpensesTbl[Category],A18,ExpensesTbl[Amount]) | C18: =VLOOKUP(A18,Categories!$A$2:$B$11,2,FALSE) | D18: =C18-B18 | E18: =IFERROR(B18/$A$7,0)
A19: Shopping | B19: =SUMIF(ExpensesTbl[Category],A19,ExpensesTbl[Amount]) | C19: =VLOOKUP(A19,Categories!$A$2:$B$11,2,FALSE) | D19: =C19-B19 | E19: =IFERROR(B19/$A$7,0)
A20: Subscriptions | B20: =SUMIF(ExpensesTbl[Category],A20,ExpensesTbl[Amount]) | C20: =VLOOKUP(A20,Categories!$A$2:$B$11,2,FALSE) | D20: =C20-B20 | E20: =IFERROR(B20/$A$7,0)
A21: Other | B21: =SUMIF(ExpensesTbl[Category],A21,ExpensesTbl[Amount]) | C21: =VLOOKUP(A21,Categories!$A$2:$B$11,2,FALSE) | D21: =C21-B21 | E21: =IFERROR(B21/$A$7,0)
A22: Total | B22: =SUM(B12:B21) | C22: =SUM(C12:C21) | D22: =SUM(D12:D21) | E22: =SUM(E12:E21)
A24: Top spending category | B24: =INDEX(A12:A21,MATCH(MAX(B12:B21),B12:B21,0))
A25: Categories over budget | B25: =COUNTIF(D12:D21,"<0")

Sheet Categories
A1: Category | B1: Monthly Budget | D1: Payment Method
A2: Rent | B2: 1450 | D2: Cash
A3: Groceries | B3: 450 | D3: Debit Card
A4: Utilities | B4: 150 | D4: Credit Card
A5: Transport | B5: 120 | D5: Bank Transfer
A6: Dining Out | B6: 150
A7: Entertainment | B7: 80
A8: Health | B8: 60
A9: Shopping | B9: 100
A10: Subscriptions | B10: 30
A11: Other | B11: 50
